youtube_sm/__init__.py
youtube_sm/__main__.py
youtube_sm/main.py
youtube_sm/version.py
youtube_sm/analyzer/__init__.py
youtube_sm/analyzer/analyzer.py
youtube_sm/analyzer/evous.py
youtube_sm/analyzer/imports.py
youtube_sm/analyzer/infoconcert.py
youtube_sm/analyzer/laquadrature.py
youtube_sm/analyzer/peertube.py
youtube_sm/analyzer/reddit.py
youtube_sm/analyzer/revolutionpermanente.py
youtube_sm/analyzer/twitch.py
youtube_sm/analyzer/twitter.py
youtube_sm/analyzer/youtube.py
youtube_sm/core/__init__.py
youtube_sm/core/commands.py
youtube_sm/core/download.py
youtube_sm/core/sock.py
youtube_sm/core/swy.py
youtube_sm/core/test.py
youtube_sm/core/thread.py
youtube_sm/core/tools.py
youtube_sm/core/write.py
youtube_sm/downloader/__init__.py
youtube_sm/downloader/evous.py
youtube_sm/downloader/infoconcert.py
youtube_sm/downloader/laquadrature.py
youtube_sm/downloader/peertube.py
youtube_sm/downloader/reddit.py
youtube_sm/downloader/revolutionpermanente.py
youtube_sm/downloader/twitch.py
youtube_sm/downloader/twitter.py
youtube_sm/downloader/youtube.py
youtube_sm-2024.6.19.dist-info/METADATA
youtube_sm-2024.6.19.dist-info/WHEEL
youtube_sm-2024.6.19.dist-info/entry_points.txt
youtube_sm-2024.6.19.dist-info/top_level.txt
youtube_sm-2024.6.19.dist-info/RECORD
