Metadata-Version: 2.1
Name: youtube_sm
Version: 2024.6.19
Summary: Youtube subscription manager
Home-page: https://github.com/sawyerf/youtube-sm
Author: Sawyerf
Author-email: sawyer.flink@protonmail.ch
License: MLP-2.0
Keywords: youtube subscription api manager html
Classifier: Topic :: Internet :: WWW/HTTP :: Indexing/Search
Classifier: Environment :: Console
Classifier: License :: OSI Approved :: Mozilla Public License 2.0 (MPL 2.0)
Classifier: Operating System :: Microsoft :: Windows
Classifier: Operating System :: POSIX :: Linux
Classifier: Programming Language :: Python
Classifier: Programming Language :: Python :: 3
Classifier: Programming Language :: Python :: 3 :: Only
